electric_estimate-0.1.0.dist-info/METADATA
electric_estimate-0.1.0.dist-info/WHEEL
electric_estimate/__init__.py
electric_estimate-0.1.0.dist-info/RECORD
